curriculumagent/__about__.py
curriculumagent/__init__.py
curriculumagent/_version.py
curriculumagent/baseline/__init__.py
curriculumagent/baseline/baseline.py
curriculumagent/baseline/evaluate.py
curriculumagent/baseline/train.py
curriculumagent/common/__init__.py
curriculumagent/common/obs_converter.py
curriculumagent/common/score_agent.py
curriculumagent/common/utilities.py
curriculumagent/junior/__init__.py
curriculumagent/junior/junior_student.py
curriculumagent/junior/hyper_parameter_search/__init__.py
curriculumagent/junior/hyper_parameter_search/advanced_junior_student.py
curriculumagent/junior/hyper_parameter_search/hyper_parameter_search_junior.py
curriculumagent/scripts/__init__.py
curriculumagent/scripts/get_seed_wcci2022.py
curriculumagent/senior/__init__.py
curriculumagent/senior/senior_student.py
curriculumagent/senior/senior_student_advanced.py
curriculumagent/senior/rllib_execution/__init__.py
curriculumagent/senior/rllib_execution/alternative_rewards.py
curriculumagent/senior/rllib_execution/senior_env_rllib.py
curriculumagent/senior/rllib_execution/senior_model_rllib.py
curriculumagent/submission/__init__.py
curriculumagent/submission/my_agent.py
curriculumagent/teacher/__init__.py
curriculumagent/teacher/collect_teacher_experience.py
curriculumagent/teacher/teacher.py
curriculumagent/teacher/submodule/__init__.py
curriculumagent/teacher/submodule/common.py
curriculumagent/teacher/submodule/encoded_action.py
curriculumagent/teacher/submodule/topology_action_search.py
curriculumagent/teacher/teachers/__init__.py
curriculumagent/teacher/teachers/teacher1.py
curriculumagent/teacher/teachers/teacher2.py
curriculumagent/teacher/teachers/teacher_n_minus_1.py
curriculumagent/teacher/teachers/teacher_sequential_actions.py
curriculumagent/teacher/teachers/tuple_triple_teacher.py
curriculumagent/tutor/__init__.py
curriculumagent/tutor/collect_divergent_powerflow.py
curriculumagent/tutor/collect_tutor_experience.py
curriculumagent/tutor/tutor.py
curriculumagent-1.0.2.dist-info/LICENSE
curriculumagent-1.0.2.dist-info/METADATA
curriculumagent-1.0.2.dist-info/WHEEL
curriculumagent-1.0.2.dist-info/namespace_packages.txt
curriculumagent-1.0.2.dist-info/top_level.txt
curriculumagent-1.0.2.dist-info/RECORD
