Metadata-Version: 2.1
Name: curriculumagent
Version: 1.0.2
Summary: CurriculumAgent is a cleanup and improved version of the NeurIPS 2020 Competition Agent by Binbinchen.The agent is build to extract action sets of the Grid2Op Environment and then use rule-based agent to train a Reinforcement Learning agent.
Author: OE224
Project-URL: GITHUB, https://github.com/FraunhoferIEE/curriculumagent/
Project-URL: Readthedocs, https://curriculumagent.readthedocs.io/en/latest/
Classifier: Development Status :: 4 - Beta
Classifier: Programming Language :: Python :: 3.10
License-File: LICENSE
Requires-Dist: grid2op >=1.9.0
Requires-Dist: numba >=0.55.1
Requires-Dist: scipy >=1.6.0
Requires-Dist: pandas >=1.3.0
Requires-Dist: pandapower >=2.8.0
Requires-Dist: tqdm >=4.62.2
Requires-Dist: LightSim2Grid >=0.7.1
Requires-Dist: lightning
Requires-Dist: ubelt >=0.10.1
Requires-Dist: gymnasium
Requires-Dist: ray ==2.5.1
Requires-Dist: ray[tune] ==2.5.1
Requires-Dist: ray[rllib] ==2.5.1
Requires-Dist: defopt
Requires-Dist: grpcio
Requires-Dist: tensorflow ==2.12.1
Requires-Dist: tensorflow-probability ==0.20.1
Requires-Dist: jupyter
Requires-Dist: l2rpn-baselines
Requires-Dist: scikit-learn
Requires-Dist: matplotlib
Requires-Dist: nni
Requires-Dist: nni[bohb]
Requires-Dist: ConfigSpace
Requires-Dist: typeguard <3
Requires-Dist: pathlib
Requires-Dist: filelock ==3.10
Provides-Extra: dev
Requires-Dist: twine ; extra == 'dev'
Requires-Dist: tabulate ; extra == 'dev'
Requires-Dist: tox ; extra == 'dev'
Requires-Dist: pytest ; extra == 'dev'
Requires-Dist: pytest-benchmark ; extra == 'dev'
Requires-Dist: pylint ; extra == 'dev'
Requires-Dist: sphinx <7 ; extra == 'dev'
Requires-Dist: sphinx-autodoc-typehints ; extra == 'dev'
Requires-Dist: sphinx-rtd-theme ; extra == 'dev'
Provides-Extra: docs
Requires-Dist: Sphinx ; extra == 'docs'
Requires-Dist: sphinx-rtd-theme ; extra == 'docs'
Requires-Dist: sphinx-autodoc-typehints ; extra == 'docs'
Provides-Extra: test
Requires-Dist: pytest ; extra == 'test'
Requires-Dist: coverage ; extra == 'test'
